[
	{
		"spanish":"girar",
		"english":"spin"
	},
	{
		"spanish":"sorpresa",
		"english":"surprise"
	},
	{
		"spanish":"maceta",
		"english":"pot"
	},
	{
		"spanish":"historiador",
		"english":"historian"
	},
	{
		"spanish":"enjuagar",
		"english":"rinse"
	},
	{
		"spanish":"casilla",
		"english":"square"
	},
	{
		"spanish":"signo",
		"english":"sign"
	},
	{
		"spanish":"profesional",
		"english":"professional"
	},
	{
		"spanish":"ficha",
		"english":"piece"
	},
	{
		"spanish":"patines",
		"english":"skates"
	},
	{
		"spanish":"historia",
		"english":"history"
	},
	{
		"spanish":"tornillo",
		"english":"screw"
	},
	{
		"spanish":"cantante",
		"english":"singer"
	},
	{
		"spanish":"insulto",
		"english":"insult"
	},
	{
		"spanish":"firma",
		"english":"signature"
	},
	{
		"spanish":"lechuga",
		"english":"lettuce"
	},
	{
		"spanish":"tiza",
		"english":"chalk"
	},
	{
		"spanish":"adoptar",
		"english":"adopt"
	},
	{
		"spanish":"pila",
		"english":"battery"
	},
	{
		"spanish":"ciudad",
		"english":"city"
	},
	{
		"spanish":"rail",
		"english":"rail"
	},
	{
		"spanish":"frontera",
		"english":"border"
	},
	{
		"spanish":"prisionero",
		"english":"prisoner"
	},
	{
		"spanish":"capullo",
		"english":"cocoon"
	},
	{
		"spanish":"anchoa",
		"english":"anchovy"
	},
	{
		"spanish":"opinión",
		"english":"opinion"
	},
	{
		"spanish":"pierna",
		"english":"leg"
	},
	{
		"spanish":"hábito",
		"english":"habit"
	},
	{
		"spanish":"hueso",
		"english":"bone"
	}
]
